[{"nome":"Tratamento","id":1,"tempo":50,"preco":59.9,"lucro":8000.0},{"nome":"Tratamento","id":2,"tempo":50,"preco":59.9,"lucro":8000.0},{"nome":"Tratamento","id":3,"tempo":50,"preco":59.9,"lucro":8000.0},{"nome":"Tratamento","id":4,"tempo":50,"preco":59.9,"lucro":8000.0},{"nome":"Tratamento","id":5,"tempo":50,"preco":59.9,"lucro":8000.0},{"nome":"Tratamento","id":6,"tempo":50,"preco":59.9,"lucro":8000.0},{"nome":"Tratamento","id":7,"tempo":50,"preco":59.9,"lucro":8000.0},{"nome":"Tratamento","id":8,"tempo":50,"preco":59.9,"lucro":8000.0},{"nome":"Tratamento","id":9,"tempo":50,"preco":59.9,"lucro":8000.0},{"nome":"Tratamento","id":10,"tempo":50,"preco":59.9,"lucro":8000.0},{"nome":"Tratamento","id":11,"tempo":50,"preco":59.9,"lucro":8000.0},{"nome":"Tratamento","id":12,"tempo":50,"preco":59.9,"lucro":8000.0},{"nome":"Tratamento","id":13,"tempo":50,"preco":59.9,"lucro":8000.0},{"nome":"Tratamento","id":14,"tempo":50,"preco":59.9,"lucro":8000.0},{"nome":"Tratamento","id":15,"tempo":50,"preco":59.9,"lucro":8000.0},{"nome":"Tratamento","id":16,"tempo":50,"preco":59.9,"lucro":8000.0},{"nome":"Tratamento","id":17,"tempo":50,"preco":59.9,"lucro":8000.0},{"nome":"Tratamento","id":18,"tempo":50,"preco":59.9,"lucro":8000.0},{"nome":"Tratamento","id":19,"tempo":50,"preco":59.9,"lucro":8000.0}]